LICENSE.txt
README.md
setup.py
Advanced_Output/__init__.py
Advanced_Output.egg-info/PKG-INFO
Advanced_Output.egg-info/SOURCES.txt
Advanced_Output.egg-info/dependency_links.txt
Advanced_Output.egg-info/top_level.txt